odoo/addons/l10n_pt_vat/README.rst
odoo/addons/l10n_pt_vat/__init__.py
odoo/addons/l10n_pt_vat/__manifest__.py
odoo/addons/l10n_pt_vat/data/account.l10n_pt.vat.exempt.reason.csv
odoo/addons/l10n_pt_vat/data/vat_adjustment_norm.xml
odoo/addons/l10n_pt_vat/i18n/l10n_pt_vat.pot
odoo/addons/l10n_pt_vat/i18n/pt.po
odoo/addons/l10n_pt_vat/models/__init__.py
odoo/addons/l10n_pt_vat/models/account_journal.py
odoo/addons/l10n_pt_vat/models/account_move.py
odoo/addons/l10n_pt_vat/models/account_tax.py
odoo/addons/l10n_pt_vat/models/l10n_pt_vat_exempt_reason.py
odoo/addons/l10n_pt_vat/models/vat_adjustment_norm.py
odoo/addons/l10n_pt_vat/readme/CONFIGURATION.rst
odoo/addons/l10n_pt_vat/readme/CONTRIBUTORS.rst
odoo/addons/l10n_pt_vat/readme/DESCRIPTION.rst
odoo/addons/l10n_pt_vat/readme/USAGE.rst
odoo/addons/l10n_pt_vat/security/ir.model.access.csv
odoo/addons/l10n_pt_vat/static/description/icon.png
odoo/addons/l10n_pt_vat/static/description/index.html
odoo/addons/l10n_pt_vat/views/account_journal_view.xml
odoo/addons/l10n_pt_vat/views/account_move_view.xml
odoo/addons/l10n_pt_vat/views/account_tax_view.xml
odoo/addons/l10n_pt_vat/views/l10n_pt_vat_exempt_reason_view.xml
odoo/addons/l10n_pt_vat/views/vat_adjustment_norm_view.xml
odoo14_addon_l10n_pt_vat-14.0.1.0.5.dist-info/METADATA
odoo14_addon_l10n_pt_vat-14.0.1.0.5.dist-info/WHEEL
odoo14_addon_l10n_pt_vat-14.0.1.0.5.dist-info/top_level.txt
odoo14_addon_l10n_pt_vat-14.0.1.0.5.dist-info/RECORD
