Metadata-Version: 2.1
Name: odoo14-addon-l10n-pt-vat
Version: 14.0.1.0.5
Summary: Portuguese VAT requirements extensions
Home-page: https://github.com/OCA/l10n-portugal
Author: Open Source Integrators, Sossia, Odoo Community Association (OCA)
Author-email: support@odoo-community.org
License: AGPL-3
Platform: UNKNOWN
Classifier: Programming Language :: Python
Classifier: Framework :: Odoo
Classifier: Framework :: Odoo :: 14.0
Classifier: License :: OSI Approved :: GNU Affero General Public License v3
Classifier: Development Status :: 5 - Production/Stable
Requires-Python: >=3.6
Requires-Dist: odoo <14.1dev,>=14.0a
